setup.py
stats_distributions_ud_scholarship/Binomialdistribution.py
stats_distributions_ud_scholarship/Gaussiandistribution.py
stats_distributions_ud_scholarship/Generaldistribution.py
stats_distributions_ud_scholarship/__init__.py
stats_distributions_ud_scholarship.egg-info/PKG-INFO
stats_distributions_ud_scholarship.egg-info/SOURCES.txt
stats_distributions_ud_scholarship.egg-info/dependency_links.txt
stats_distributions_ud_scholarship.egg-info/not-zip-safe
stats_distributions_ud_scholarship.egg-info/top_level.txt