Metadata-Version: 1.0
Name: stats-distributions-ud-scholarship
Version: 0.1
Summary: Gaussian distributions and Binomial dsitribution
Home-page: UNKNOWN
Author: Peter Olaomi
Author-email: p.olaomi@gmail.com
License: UNKNOWN
Platform: UNKNOWN
